postalcodeareas_fi/__init__.py
postalcodeareas_fi/data.py.in
postalcodeareas_fi/rebuild.py
postalcodeareas_fi/util.py
postalcodeareas-fi-0.1.dist-info/LICENSE.txt
postalcodeareas-fi-0.1.dist-info/WHEEL
postalcodeareas-fi-0.1.dist-info/METADATA
postalcodeareas-fi-0.1.dist-info/RECORD
